rest_client_micro/__init__.py
rest_client_micro/_utils.py
rest_client_micro/base_rest_api.py
rest_client_micro/basic_auth.py
rest_client_micro/response.py
rest_client_micro/rest_client.py
rest_client_micro/rest_object.py
rest_client_micro-0.3.22.dist-info/METADATA
rest_client_micro-0.3.22.dist-info/WHEEL
rest_client_micro-0.3.22.dist-info/licenses/LICENSE
rest_client_micro-0.3.22.dist-info/RECORD
