Metadata-Version: 2.4
Name: rest_client_micro
Version: 0.3.22
Summary: A micro rest client
Author: Samuel Shiels
License-File: LICENSE
Classifier: License :: OSI Approved :: MIT License
Classifier: Operating System :: POSIX :: Linux
Classifier: Programming Language :: Python :: 3
Requires-Python: >=3.11.5
Requires-Dist: diskcache>=5.6.3
Requires-Dist: jsonpickle>=3.0.2
Requires-Dist: requests>=2.31.0
